com_tools/__init__.py
com_tools/_protocols.py
com_tools/base.py
com_tools/loggers.py
com_tools/demo/__init__.py
com_tools/demo/commands.py
com_tools/iec62056/__init__.py
com_tools/iec62056/commands.py
com_tools/modbus/__init__.py
com_tools/modbus/client.py
com_tools/modbus/commands.py
com_tools/profiles/__init__.py
com_tools/profiles/commands.py
com_tools/utils/__init__.py
com_tools/utils/enums.py
com_tools/utils/listings.py
com_tools/utils/storage.py
com_tools-0.1.0.dist-info/METADATA
com_tools-0.1.0.dist-info/WHEEL
com_tools-0.1.0.dist-info/entry_points.txt
com_tools-0.1.0.dist-info/RECORD
