Metadata-Version: 2.4
Name: com-tools
Version: 0.1.0
Summary: A generic CLI package to test communication with industrial devices.
Author-email: Adrien Delhaye <adrien.delhaye@memoco.eu>
Requires-Python: >=3.13
Requires-Dist: click>=8.2.1
Requires-Dist: faststream[cli,rabbit]>=0.5.48
Requires-Dist: loguru>=0.7.3
Requires-Dist: pydantic-settings>=2.10.1
Requires-Dist: pydantic>=2.11.7
Requires-Dist: pymodbus>=3.11.0
Requires-Dist: pyserial>=3.5
